gappr10/__init__.py
gappr10/gappr10.py
gappr10-0.1.dist-info/LICENSE
gappr10-0.1.dist-info/WHEEL
gappr10-0.1.dist-info/METADATA
gappr10-0.1.dist-info/RECORD
