Metadata-Version: 2.1
Name: gappr10
Version: 0.1
Summary: A simple utility to work with your personal data collected by the 
Author-email: Brock Tibert <btibert3@gmail.com>
Classifier: License :: OSI Approved :: MIT License
Project-URL: Home, https://brocktibert.com/
